LICENSE
dexom_python/__init__.py
dexom_python/cluster_utils/Snakefile
dexom_python/cluster_utils/__init__.py
dexom_python/cluster_utils/cluster_config.yaml
dexom_python/cluster_utils/cluster_install_dexom_python.sh
dexom_python/cluster_utils/legacy/__init__.py
dexom_python/cluster_utils/legacy/dexom_cluster_results.py
dexom_python/cluster_utils/legacy/write_cluster_scripts.py
dexom_python/cluster_utils/slurm_example_gpr.sh
dexom_python/cluster_utils/snakemake_utils.smk
dexom_python/cluster_utils/solution_compilation.py
dexom_python/cluster_utils/submit.py
dexom_python/cluster_utils/submit_slurm.sh
dexom_python/default_parameter_values.py
dexom_python/enum_functions/__init__.py
dexom_python/enum_functions/diversity_enum_functions.py
dexom_python/enum_functions/enumeration.py
dexom_python/enum_functions/icut_functions.py
dexom_python/enum_functions/maxdist_functions.py
dexom_python/enum_functions/permutation_functions.py
dexom_python/enum_functions/riptide_functions.py
dexom_python/enum_functions/rxn_enum_functions.py
dexom_python/gpr_rules.py
dexom_python/imat_functions.py
dexom_python/main.py
dexom_python/model_functions.py
dexom_python/pathway_enrichment.py
dexom_python/result_functions.py
dexom_python/toy_models.py
dexom_python-2.2.dist-info/LICENSE
dexom_python-2.2.dist-info/METADATA
dexom_python-2.2.dist-info/WHEEL
dexom_python-2.2.dist-info/RECORD
