Metadata-Version: 2.1
Name: dexom-python
Version: 2.2
Summary: DEXOM implementation in python using cobrapy
Home-page: https://forge.inrae.fr/metexplore/cbm/dexom-python
License: GPL-3.0
Author: Maximilian Stingl
Author-email: maximilian.stingl@inrae.fr
Requires-Python: >=3.7,<3.11
Classifier: License :: OSI Approved :: GNU General Public License v3 (GPLv3)
Classifier: Programming Language :: Python :: 3
Classifier: Programming Language :: Python :: 3.7
Classifier: Programming Language :: Python :: 3.8
Classifier: Programming Language :: Python :: 3.9
Classifier: Programming Language :: Python :: 3.10
Requires-Dist: cobra (>=0.26.3,<0.27.0)
Requires-Dist: matplotlib (>=3.5.1,<4.0.0)
Requires-Dist: numpy (>=1.20,<1.24)
Requires-Dist: scikit-learn (>=1.0.2,<2.0.0)
Requires-Dist: scipy (>=1.7,<2.0)
Requires-Dist: statsmodels (>=0.13.2,<0.14.0)
Requires-Dist: swiglpk (==5.0.5)
Requires-Dist: symengine (>=0.9.2,<0.10.0)
Project-URL: Repository, https://forge.inrae.fr/metexplore/cbm/dexom-python
